LICENSE
README.md
pyproject.toml
requirements.txt
kcpdi/__init__.py
kcpdi/kcp_ds.py
kcpdi/kcp_ss_learner.py
kcpdi/kcp_v.py
kcpdi/utils.py
kcpdi.egg-info/PKG-INFO
kcpdi.egg-info/SOURCES.txt
kcpdi.egg-info/dependency_links.txt
kcpdi.egg-info/requires.txt
kcpdi.egg-info/top_level.txt