Metadata-Version: 2.4
Name: kcpdi
Version: 0.1.0
Summary: Linear kernel anomaly/change-point detection in multidimensional time series data
Author: Kevin Bleakley
Author-email: kevin.bleakley@inria.fr
License-Expression: MPL-2.0
Project-URL: Homepage, https://confianceai.github.io/kernel-change-point-detection
Project-URL: Documentation, https://confianceai.github.io/kernel-change-point-detection
Project-URL: Repository, https://github.com/confianceai/kernel-change-point-detection
Requires-Python: <3.13,>=3.11
License-File: LICENSE
Requires-Dist: numpy==2.2.6
Requires-Dist: scipy==1.16.0
Requires-Dist: pandas==2.3.1
Requires-Dist: matplotlib==3.10.5
Requires-Dist: scikit-learn==1.7.1
Requires-Dist: ipykernel==6.30.1
Requires-Dist: ruptures==1.1.9
Dynamic: license-file
